django_react_kit/__init__.py
django_react_kit/apps.py
django_react_kit/urls.py
django_react_kit/views.py
django_react_kit/frontend/main.tsx
django_react_kit/frontend/package.json
django_react_kit/frontend/ssr.js
django_react_kit/frontend/app/layout.tsx
django_react_kit/frontend/app/page.tsx
django_react_kit/frontend/app/about/page.tsx
django_react_kit/management/__init__.py
django_react_kit/management/commands/__init__.py
django_react_kit/management/commands/reactbuild.py
django_react_kit/templates/django_react_kit/index.html
django_react_kit-1.0.2.dist-info/licenses/LICENSE
django_react_kit-1.0.2.dist-info/METADATA
django_react_kit-1.0.2.dist-info/WHEEL
django_react_kit-1.0.2.dist-info/entry_points.txt
django_react_kit-1.0.2.dist-info/top_level.txt
django_react_kit-1.0.2.dist-info/RECORD
