Metadata-Version: 2.4
Name: django-react-kit
Version: 1.0.2
Summary: Server-Side Rendering for React components in Django
Home-page: https://github.com/django-react-kit/django-react-kit
Author: Django React Kit Team
Author-email: hello@djangoreactkit.com
License: MIT
Project-URL: Bug Reports, https://github.com/cyberwizdev/cyberwizdev/issues
Project-URL: Source, https://github.com/cyberwizdev/django-react-kit
Project-URL: Documentation, https://django-react-kit.readthedocs.io/
Keywords: django react ssr server-side-rendering frontend
Classifier: Development Status :: 4 - Beta
Classifier: Framework :: Django
Classifier: Framework :: Django :: 3.2
Classifier: Framework :: Django :: 4.0
Classifier: Framework :: Django :: 4.1
Classifier: Framework :: Django :: 4.2
Classifier: Intended Audience :: Developers
Classifier: License :: OSI Approved :: MIT License
Classifier: Operating System :: OS Independent
Classifier: Programming Language :: Python :: 3
Classifier: Programming Language :: Python :: 3.8
Classifier: Programming Language :: Python :: 3.9
Classifier: Programming Language :: Python :: 3.10
Classifier: Programming Language :: Python :: 3.11
Classifier: Topic :: Software Development :: Libraries :: Python Modules
Classifier: Topic :: Internet :: WWW/HTTP :: Dynamic Content
Requires-Python: >=3.8
License-File: LICENSE
Requires-Dist: Django
Dynamic: author
Dynamic: author-email
Dynamic: classifier
Dynamic: description
Dynamic: description-content-type
Dynamic: home-page
Dynamic: keywords
Dynamic: license-file
Dynamic: project-url
Dynamic: requires-dist
Dynamic: requires-python
Dynamic: summary
